<?xml version="1.0" encoding="UTF-8" standalone="yes"?>
<eventposdef>
    <event name="AnimalBear" />
    <event name="AnimalCattle" />
    <event name="AnimalDeer" />
    <event name="AnimalHen" />
    <event name="AnimalPig" />
    <event name="AnimalRoeDeer" />
    <event name="AnimalWildBoar" />
    <event name="AnimalWolf" />

    <event name="InfectedArmy" />
    <event name="InfectedArmyHeavy" />
    <event name="InfectedCity" />
    <event name="InfectedCityTier1" />
    <event name="InfectedCityTier2" />
    <event name="InfectedCityTier3" />
    <event name="InfectedFirefighter" />
    <event name="InfectedIndustrial" />
    <event name="InfectedMedic" />
    <event name="InfectedNBCGreen" />
    <event name="InfectedNBCPurple" />
    <event name="InfectedNBCRed" />
    <event name="InfectedNBC" />
    <event name="InfectedNBCBlack" />
    <event name="InfectedPolice" />
    <event name="InfectedPoliceHeavy" />
    <event name="InfectedPrisoner" />
    <event name="InfectedReligious" />
    <event name="InfectedSolitude" />
    <event name="InfectedVillage" />
    <event name="InfectedVillageTier1" />

    <event name="Static_CCS_Capsule_Vending_Machine">
        <zone smin="0" smax="0" dmin="0" dmax="0" r="0" />

        <!-- East Hashima - Capsule Vending Machine -->
        <pos x="3307.903320" y="2.140393" z="2713.867432" a="20.000000" />
        <pos x="3573.004150" y="2.080000" z="2807.814209" a="90.000000" />
        <pos x="3678.009277" y="2.060000" z="2815.920410" a="230.000000" />
        <pos x="3706.251953" y="2.060000" z="2498.926758" a="20.000000" />
        <pos x="3734.547607" y="2.120000" z="2782.248779" a="200.000000" />

        <!-- New Hashima - Capsule Vending Machine -->
        <pos x="2459.774170" y="8.090000" z="2401.082000" a="45.000000" />
        <pos x="2474.530518" y="9.150000" z="2419.914000" a="180.000000" />
        <pos x="2500.354492" y="9.200000" z="2506.291504" a="180.000000" />
        <pos x="2509.336426" y="8.100000" z="2515.707000" a="180.000000" />
        <pos x="2535.756836" y="13.800000" z="2520.025635" a="0.000000" />

        <!-- West Hashima - Capsule Vending Machine -->
        <pos x="1578.402222" y="4.560000" z="2274.481201" a="90.000000" />
        <pos x="1693.413086" y="4.580000" z="2210.800293" a="270.000000" />
        <pos x="1700.609000" y="4.500000" z="1752.844727" a="358.000000" />
        <pos x="1725.997681" y="4.590000" z="2889.262451" a="0.000000" />
        <pos x="1807.348022" y="22.390000" z="2233.815674" a="90.000000" />
    </event>

    <event name="Loot" />

    <!-- TO DO: SORT THESE -->
    <event name="StaticHeliCrash">
        <zone smin="1" smax="3" dmin="3" dmax="5" r="45" />
        <pos x="893" z="1896" />
        <pos x="2625" z="2513" />
        <pos x="3391" z="2512" />
    </event>

    <event name="TrajectoryApple" />
    <event name="TrajectoryCanina" />
    <event name="TrajectoryConiferous" />
    <event name="TrajectoryDeciduous" />
    <event name="TrajectoryHumus" />
    <event name="TrajectoryPear" />
    <event name="TrajectoryPlum" />
    <event name="TrajectorySambucus" />
    <event name="TrajectoryStones" />
</eventposdef>
